[
  {
    "id": "4.1-q2",
    "objectiveId": "4.1",
    "question": "Using the referenced source exhibit, what is the inside local IP address?",
    "reason": "exhibit-dependent",
    "shelvedAt": "2026-06-14",
    "notes": "NAT topology — convert to inline text exhibit later"
  },
  {
    "id": "4.1-q3",
    "objectiveId": "4.1",
    "question": "Using the referenced source exhibit, what is the inside global IP address?",
    "reason": "exhibit-dependent",
    "shelvedAt": "2026-06-14",
    "notes": "NAT topology — convert to inline text exhibit later"
  },
  {
    "id": "4.1-q4",
    "objectiveId": "4.1",
    "question": "Using the referenced source exhibit, what is the outside global IP address?",
    "reason": "exhibit-dependent",
    "shelvedAt": "2026-06-14",
    "notes": "NAT topology — convert to inline text exhibit later"
  },
  {
    "id": "4.1-q7",
    "objectiveId": "4.1",
    "question": "Using the referenced source exhibit, which command will configure static NAT for the internal web server?",
    "reason": "exhibit-dependent",
    "shelvedAt": "2026-06-14",
    "notes": "NAT topology — convert to inline text exhibit later"
  },
  {
    "id": "4.1-q8",
    "objectiveId": "4.1",
    "question": "Using the referenced source exhibit, the enterprise owns the address block of 179.43.44.0/28. Which command create a NAT pool for Dynamic NAT?",
    "reason": "exhibit-dependent",
    "shelvedAt": "2026-06-14",
    "notes": "NAT topology — convert to inline text exhibit later"
  },
  {
    "id": "4.1-q12",
    "objectiveId": "4.1",
    "question": "Using the referenced source exhibit, which command will configure Port Address Translation?",
    "reason": "exhibit-dependent",
    "shelvedAt": "2026-06-14",
    "notes": "NAT topology — convert to inline text exhibit later"
  },
  {
    "id": "obj-4.5-source-q008",
    "objectiveId": "4.5",
    "question": "What severity is being logged to in the referenced source exhibit?",
    "reason": "exhibit-dependent",
    "shelvedAt": "2026-06-14",
    "notes": ""
  },
  {
    "id": "obj-4.6-source-q005",
    "objectiveId": "4.6",
    "question": "Using the referenced source exhibit, what is required on the network to allow Host A to receive an IP address from the existing DHCP server?",
    "reason": "exhibit-dependent",
    "shelvedAt": "2026-06-14",
    "notes": ""
  }
]